MANIFEST.in
setup.py
flask_spawn.egg-info/PKG-INFO
flask_spawn.egg-info/SOURCES.txt
flask_spawn.egg-info/dependency_links.txt
flask_spawn.egg-info/entry_points.txt
flask_spawn.egg-info/pbr.json
flask_spawn.egg-info/requires.txt
flask_spawn.egg-info/top_level.txt
flaskspawn/__init__.py
flaskspawn/spawn.py
flaskspawn/cookiecutters/small/cookiecutter.json
flaskspawn/cookiecutters/small/{{cookiecutter.repo_name}}/.gitignore
flaskspawn/cookiecutters/small/{{cookiecutter.repo_name}}/README.md
flaskspawn/cookiecutters/small/{{cookiecutter.repo_name}}/config.py
flaskspawn/cookiecutters/small/{{cookiecutter.repo_name}}/config.pyc
flaskspawn/cookiecutters/small/{{cookiecutter.repo_name}}/requirements.txt
flaskspawn/cookiecutters/small/{{cookiecutter.repo_name}}/run.py
flaskspawn/cookiecutters/small/{{cookiecutter.repo_name}}/run.sh
flaskspawn/cookiecutters/small/{{cookiecutter.repo_name}}/test.sh
flaskspawn/cookiecutters/small/{{cookiecutter.repo_name}}/application/__init__.py
flaskspawn/cookiecutters/small/{{cookiecutter.repo_name}}/application/__init__.pyc
flaskspawn/cookiecutters/small/{{cookiecutter.repo_name}}/application/views.py
flaskspawn/cookiecutters/small/{{cookiecutter.repo_name}}/application/views.pyc
flaskspawn/cookiecutters/small/{{cookiecutter.repo_name}}/application/__pycache__/__init__.cpython-34.pyc
flaskspawn/cookiecutters/small/{{cookiecutter.repo_name}}/application/static/css/base.css
flaskspawn/cookiecutters/small/{{cookiecutter.repo_name}}/application/templates/base.html
flaskspawn/cookiecutters/small/{{cookiecutter.repo_name}}/tests/__init__.py
flaskspawn/cookiecutters/small/{{cookiecutter.repo_name}}/tests/__init__.pyc
flaskspawn/cookiecutters/small/{{cookiecutter.repo_name}}/tests/test_app.py
flaskspawn/cookiecutters/small/{{cookiecutter.repo_name}}/tests/__pycache__/__init__.cpython-34.pyc
flaskspawn/cookiecutters/small/{{cookiecutter.repo_name}}/tests/__pycache__/test_app.cpython-27-PYTEST.pyc
flaskspawn/cookiecutters/small/{{cookiecutter.repo_name}}/tests/__pycache__/test_app.cpython-34-PYTEST.pyc
flaskspawn/snippets/__init__.py
flaskspawn/snippets/__init__.pyc
flaskspawn/snippets/file_routines.py
flaskspawn/snippets/file_routines.pyc
flaskspawn/snippets/snippets.py
