Metadata-Version: 1.0
Name: flask-spawn
Version: 0.1.11
Summary: Generate new flask projects quickly and easily, in a variety of customisable structures.
Home-page: https://github.com/Skablam/flask-spawn
Author: Matthew Pease
Author-email: stainlesssteelmatt@gmail.com
License: MIT
Platform: UNKNOWN
